envforge/__init__.py
envforge/cli/__init__.py
envforge/cli/main.py
envforge/cli/security.py
envforge/core/__init__.py
envforge/core/config.py
envforge/core/detector.py
envforge/core/restorer.py
envforge/core/security.py
envforge/core/sync.py
envforge/storage/__init__.py
envforge/storage/local.py
envforge/storage/secure.py
envforge/utils/__init__.py
envforge-0.1.3.dist-info/licenses/LICENSE
envforge-0.1.3.dist-info/METADATA
envforge-0.1.3.dist-info/WHEEL
envforge-0.1.3.dist-info/entry_points.txt
envforge-0.1.3.dist-info/top_level.txt
envforge-0.1.3.dist-info/RECORD
