Metadata-Version: 2.4
Name: envforge
Version: 0.1.3
Summary: EnvForge - Forge, sync and restore complete development environments in minutes
Home-page: https://github.com/bernardoamorimalvarenga/envforge
Author: Bernardo Amorim Alvarenga
Author-email: amorimbernardogame@gmail.com
Project-URL: Bug Reports, https://github.com/bernardoamorimalvarenga/envforge/issues
Project-URL: Source, https://github.com/bernardoamorimalvarenga/envforge
Project-URL: Documentation, https://github.com/bernardoamorimalvarenga/envforge#readme
Project-URL: Changelog, https://github.com/bernardoamorimalvarenga/envforge/blob/main/CHANGELOG.md
Keywords: linux development environment backup sync cli devops dotfiles packages git automation envforge
Platform: Linux
Classifier: Development Status :: 4 - Beta
Classifier: Intended Audience :: Developers
Classifier: License :: OSI Approved :: MIT License
Classifier: Operating System :: POSIX :: Linux
Classifier: Programming Language :: Python :: 3
Classifier: Programming Language :: Python :: 3.8
Classifier: Programming Language :: Python :: 3.9
Classifier: Programming Language :: Python :: 3.10
Classifier: Programming Language :: Python :: 3.11
Classifier: Programming Language :: Python :: 3.12
Classifier: Topic :: Software Development
Classifier: Topic :: Software Development :: Libraries :: Python Modules
Classifier: Topic :: System :: Systems Administration
Classifier: Topic :: System :: Archiving :: Backup
Classifier: Topic :: Utilities
Classifier: Environment :: Console
Requires-Python: >=3.8
License-File: LICENSE
Requires-Dist: click>=8.0.0
Requires-Dist: rich>=13.0.0
Requires-Dist: pyyaml>=6.0
Requires-Dist: gitpython>=3.1.0
Requires-Dist: psutil>=5.9.0
Requires-Dist: cryptography
Provides-Extra: dev
Requires-Dist: pytest>=7.0.0; extra == "dev"
Requires-Dist: pytest-cov>=4.0.0; extra == "dev"
Requires-Dist: black>=23.0.0; extra == "dev"
Requires-Dist: isort>=5.12.0; extra == "dev"
Requires-Dist: flake8>=6.0.0; extra == "dev"
Requires-Dist: autoflake>=2.0.0; extra == "dev"
Dynamic: author
Dynamic: author-email
Dynamic: classifier
Dynamic: description
Dynamic: description-content-type
Dynamic: home-page
Dynamic: keywords
Dynamic: license-file
Dynamic: platform
Dynamic: project-url
Dynamic: provides-extra
Dynamic: requires-dist
Dynamic: requires-python
Dynamic: summary
